sia/__init__.py
sia/sia.py
tests/__init__.py
tests/test_sia.py
timeleap_sia-1.0.1.dist-info/LICENSE
timeleap_sia-1.0.1.dist-info/METADATA
timeleap_sia-1.0.1.dist-info/WHEEL
timeleap_sia-1.0.1.dist-info/top_level.txt
timeleap_sia-1.0.1.dist-info/RECORD
