Metadata-Version: 2.1
Name: timeleap-sia
Version: 1.0.1
Summary: Sia serialization for Python
Home-page: https://github.com/TimeleapLabs/py-sia
Author: Pouya Eghbali
Author-email: pouya@timeleap.swiss
Classifier: Programming Language :: Python :: 3
Classifier: License :: OSI Approved :: Apache Software License
Classifier: Operating System :: OS Independent
Requires-Python: >=3.6
License-File: LICENSE
